babar/__init__.py
babar-0.0.0.dist-info/DESCRIPTION.rst
babar-0.0.0.dist-info/METADATA
babar-0.0.0.dist-info/RECORD
babar-0.0.0.dist-info/WHEEL
babar-0.0.0.dist-info/metadata.json
babar-0.0.0.dist-info/top_level.txt
