Metadata-Version: 2.0
Name: babar
Version: 0.0.0
Summary: Elephants never forget.
Home-page: https://github.com/samuela/babar
Author: Samuel Ainsworth
Author-email: skainsworth@gmail.com
License: UNKNOWN
Platform: UNKNOWN
